{
  "document": {
    "blocks": [
      {
        "key": "fmdra",
        "text": "FontoXML",
        "type": "header-one",
        "depth": 0,
        "inlineStyleRanges": [],
        "entityRanges": [],
        "data": {}
      },
      {
        "key": "9jmua",
        "text": "ffdhdfhdf",
        "type": "paragraph",
        "depth": 0,
        "inlineStyleRanges": [],
        "entityRanges": [],
        "data": {}
      },
      {
        "key": "dur7q",
        "text": "",
        "type": "paragraph",
        "depth": 0,
        "inlineStyleRanges": [],
        "entityRanges": [],
        "data": {}
      }
    ],
    "entityMap": {}
  },
  "editor": {
    "status": "offline"
  }
}